simgui/__init__.py
simgui/mockaudio.py
simgui/transforms.py
simgui-1.5.2.dist-info/LICENSE
simgui-1.5.2.dist-info/METADATA
simgui-1.5.2.dist-info/WHEEL
simgui-1.5.2.dist-info/top_level.txt
simgui-1.5.2.dist-info/RECORD
