Metadata-Version: 2.1
Name: simgui
Version: 1.5.2
Summary: A simple GUI API (wrapper around PySide6) for Python learners to build simple yet interesting event driven apps.
Home-page: https://github.com/freemant2000/simgui
Author: Kent Tong
Author-email: kent.tong.mo@gmail.com
Project-URL: Bug Tracker, https://github.com/freemant2000/simgui/issues
Classifier: Programming Language :: Python :: 3
Classifier: License :: OSI Approved :: GNU General Public License v3 (GPLv3)
Classifier: Operating System :: OS Independent
Requires-Python: >=3.6
License-File: LICENSE
Requires-Dist: PySide6
